LICENSE
MANIFEST.in
README
setup.py
bin/__init__.py
bin/check_catalog.py
bin/check_files.py
bin/check_url.py
thredds_security_test/__init__.py
thredds_security_test.egg-info/PKG-INFO
thredds_security_test.egg-info/SOURCES.txt
thredds_security_test.egg-info/dependency_links.txt
thredds_security_test.egg-info/entry_points.txt
thredds_security_test.egg-info/top_level.txt
thredds_security_test/lib/__init__.py
thredds_security_test/lib/catalog_access.py
thredds_security_test/lib/catalog_parser.py
thredds_security_test/lib/configuration.py
thredds_security_test/lib/dataset_access.py
thredds_security_test/lib/dataset_config.py
thredds_security_test/lib/file_access.py
thredds_security_test/lib/httpget.py
thredds_security_test/lib/results.py
thredds_security_test/lib/service_config.py
thredds_security_test/lib/url_util.py
thredds_security_test/lib/xml_util.py
thredds_security_test/test/__init__.py
thredds_security_test/test/test_access.py