Metadata-Version: 1.0
Name: thredds-security-test
Version: 0.1.0
Summary: THREDDS Data Server security configuration test utilities
Home-page: UNKNOWN
Author: Richard Wilkinson
Author-email: UNKNOWN
License: BSD - See LICENCE file for details
Platform: UNKNOWN
